harp/__init__.py
harp/common.yml
harp/io.py
harp/model.py
harp/reader.py
harp/schema.py
harp/typing.py
harp_python-0.4.1.dist-info/licenses/LICENSE
harp_python-0.4.1.dist-info/METADATA
harp_python-0.4.1.dist-info/WHEEL
harp_python-0.4.1.dist-info/top_level.txt
harp_python-0.4.1.dist-info/RECORD
