Metadata-Version: 2.4
Name: harp-python
Version: 0.4.1
Summary: A low-level interface for loading binary Harp protocol data
Author-email: Goncalo Lopes <g.lopes@neurogears.org>
License-Expression: MIT
Project-URL: Bug Tracker, https://github.com/harp-tech/harp-python/issues
Project-URL: Source Code, https://github.com/harp-tech/harp-python
Classifier: Development Status :: 4 - Beta
Classifier: Programming Language :: Python
Classifier: Programming Language :: Python :: 3
Classifier: Programming Language :: Python :: 3.9
Classifier: Programming Language :: Python :: 3.10
Classifier: Operating System :: OS Independent
Requires-Python: >=3.9.0
License-File: LICENSE
Requires-Dist: pydantic-yaml
Requires-Dist: pandas
Provides-Extra: dev
Requires-Dist: datamodel-code-generator; extra == "dev"
Requires-Dist: pandas-stubs; extra == "dev"
Requires-Dist: pytest; extra == "dev"
Requires-Dist: pytest-cov; extra == "dev"
Requires-Dist: pyright; extra == "dev"
Requires-Dist: ruff; extra == "dev"
Requires-Dist: codespell; extra == "dev"
Provides-Extra: jupyter
Requires-Dist: ipykernel; extra == "jupyter"
Requires-Dist: matplotlib; extra == "jupyter"
Dynamic: license-file
